fh_plotly/__init__.py
fh_plotly/p2fh.py
fh_plotly-0.2.4.dist-info/LICENSE
fh_plotly-0.2.4.dist-info/METADATA
fh_plotly-0.2.4.dist-info/WHEEL
fh_plotly-0.2.4.dist-info/top_level.txt
fh_plotly-0.2.4.dist-info/RECORD
