Metadata-Version: 2.2
Name: fh-plotly
Version: 0.2.4
Summary: Plotly in FastHTML
Author-email: Carlo Lepelaars <info@carlolepelaars.nl>
License: MIT License
Requires-Python: <4,>=3.10
License-File: LICENSE
Requires-Dist: python-fasthtml>=0.12.0
Requires-Dist: plotly>=6.0.0
